pancakes/__init__.py
pancakes/cli.py
pancakes/pancakes.py
pancakes/version.py
pancakes-0.2.0.dist-info/METADATA
pancakes-0.2.0.dist-info/RECORD
pancakes-0.2.0.dist-info/WHEEL
pancakes-0.2.0.dist-info/entry_points.txt
pancakes-0.2.0.dist-info/top_level.txt
