Metadata-Version: 2.1
Name: pancakes
Version: 0.2.0
Summary: Pancake making utility
Home-page: https://github.com/gloc-mike/pancakes
Author: Michael B
Author-email: online.alias.mb@me.com
License: MIT license
Keywords: pancakes
Platform: UNKNOWN
Classifier: Development Status :: 2 - Pre-Alpha
Classifier: Intended Audience :: Developers
Classifier: License :: OSI Approved :: MIT License
Classifier: Natural Language :: English
Classifier: Programming Language :: Python :: 3
Classifier: Programming Language :: Python :: 3.7
Requires-Dist: Click (>=6.0)
